starfruit/__about__.py
starfruit/__init__.py
starfruit/app.py
starfruit/app.tcss
starfruit/app_logs.py
starfruit/app_main.py
starfruit/entry_points.py
starfruit/logger.py
starfruit/proc_systray.py
starfruit/proc_webview.py
starfruit/server.py
starfruit/server_webview.py
starfruit/systray.py
starfruit/static/index.html
starfruit/static/assets/index-BpT54FNp.css
starfruit/static/assets/index-DXjCHnq7.js
starfruit/utils/__init__.py
starfruit/utils/check_update.py
starfruit/utils/const.py
starfruit/utils/env.py
starfruit/utils/get_app_dir.py
starfruit/utils/get_version.py
starfruit/utils/internal_post.py
starfruit-0.0.1.dist-info/METADATA
starfruit-0.0.1.dist-info/WHEEL
starfruit-0.0.1.dist-info/entry_points.txt
starfruit-0.0.1.dist-info/licenses/LICENSE
starfruit-0.0.1.dist-info/RECORD
